pyramid_services_viewmapper/__init__.py
pyramid_services_viewmapper-1.1.0.dist-info/LICENSE
pyramid_services_viewmapper-1.1.0.dist-info/METADATA
pyramid_services_viewmapper-1.1.0.dist-info/WHEEL
pyramid_services_viewmapper-1.1.0.dist-info/RECORD
