Metadata-Version: 2.1
Name: pyramid-services-viewmapper
Version: 1.1.0
Summary: View mapper for use with pyramid_services.
Author: Olly Parton
Author-email: mysticdragonfly@hotmail.co.uk
Requires-Python: >=3.7
Classifier: Programming Language :: Python :: 3
Classifier: Programming Language :: Python :: 3.7
Classifier: Programming Language :: Python :: 3.8
Classifier: Programming Language :: Python :: 3.9
Classifier: Programming Language :: Python :: 3.10
Classifier: Programming Language :: Python :: 3.11
Requires-Dist: pyramid-services (>=2.0)
